classical_doa/__init__.py
classical_doa/arrays.py
classical_doa/plot.py
classical_doa/signals.py
classical_doa/algorithm/__init__.py
classical_doa/algorithm/broadband.py
classical_doa/algorithm/esprit_based.py
classical_doa/algorithm/music_based.py
classical_doa/algorithm/sparse.py
classical_doa/algorithm/utils.py
classical_doa-1.3.0.dist-info/LICENSE
classical_doa-1.3.0.dist-info/METADATA
classical_doa-1.3.0.dist-info/WHEEL
classical_doa-1.3.0.dist-info/top_level.txt
classical_doa-1.3.0.dist-info/RECORD
